[
	{
		"id": "2-163107997",
		"title": "점심시간 짤막하게",
		"uploader": "HANA",
		"channel_id": "221",
		"channel_url": "https://weverse.io/fiftyfifty",
		"duration": 1479.0,
		"duration_string": "24:39",
		"upload_date": "20250819",
		"timestamp": 1755574596,
		"view_count": 7547,
		"like_count": 52610,
		"release_timestamp": 1755574596,
		"comment_count": 24,
		"description": "",
		"tags": null,
		"categories": null,
		"live_status": "was_live",
		"was_live": true,
		"is_live": false,
		"media_type": "video",
		"webpage_url": "https://weverse.io/fiftyfifty/live/2-163107997",
		"subtitles": null,
		"thumbnail": "https://phinf.wevpstatic.net/MjAyNTA4MTlfMyAg/MDAxNzU1NTc2MDg2NDQz.b5mDw61SifIJg-Sv7GUPFSc0AFjFZ_9BrgyH7Y2Armsg.1CGYSNId7iacHyDSrXxMelMIzs514Mgr4O-Yloa1SCIg.JPEG/thumb.jpg",
		"thumbnails": [
			{
				"url": "https://phinf.wevpstatic.net/MjAyNTA4MTlfMyAg/MDAxNzU1NTc2MDg2NDQz.b5mDw61SifIJg-Sv7GUPFSc0AFjFZ_9BrgyH7Y2Armsg.1CGYSNId7iacHyDSrXxMelMIzs514Mgr4O-Yloa1SCIg.JPEG/thumb.jpg",
				"id": "0"
			}
		],
		"cast": ["HANA"],
		"platform": "weverse",
		"series": null
	},
	{
		"id": "1-163046460",
		"title": "Code name : 🐓🦶",
		"uploader": "FIFTY FIFTY",
		"channel_id": "221",
		"channel_url": "https://weverse.io/fiftyfifty",
		"duration": 3448.0,
		"duration_string": "57:28",
		"upload_date": "20250817",
		"timestamp": 1755425503,
		"view_count": 11179,
		"like_count": 102000,
		"release_timestamp": 1755425503,
		"comment_count": 28,
		"description": "",
		"tags": null,
		"categories": null,
		"live_status": "was_live",
		"was_live": true,
		"is_live": false,
		"media_type": "video",
		"webpage_url": "https://weverse.io/fiftyfifty/live/1-163046460",
		"subtitles": null,
		"thumbnail": "https://phinf.wevpstatic.net/MjAyNTA4MTdfMTkz/MDAxNzU1NDI1NDg2NzQ0.yNCDPiVpJOLEMStrBD-Vu9YnEvdQkiZvS-4hj-MEPC0g.YlxxXCiepvo-h8Smcga4q8RWYkUVcA8ljwd6bdCSYDMg.JPEG/image.jpg",
		"thumbnails": [
			{
				"url": "https://phinf.wevpstatic.net/MjAyNTA4MTdfMTkz/MDAxNzU1NDI1NDg2NzQ0.yNCDPiVpJOLEMStrBD-Vu9YnEvdQkiZvS-4hj-MEPC0g.YlxxXCiepvo-h8Smcga4q8RWYkUVcA8ljwd6bdCSYDMg.JPEG/image.jpg",
				"id": "0"
			}
		],
		"cast": ["KEENA"],
		"platform": "weverse",
		"series": null
	},
	{
		"id": "2-162812531",
		"title": "다시 왔오☘️⭐️",
		"uploader": "HANA",
		"channel_id": "221",
		"channel_url": "https://weverse.io/fiftyfifty",
		"duration": 4079.0,
		"duration_string": "1:07:59",
		"upload_date": "20250811",
		"timestamp": 1754899239,
		"view_count": 17766,
		"like_count": 93432,
		"release_timestamp": 1754899239,
		"comment_count": 26,
		"description": "",
		"tags": null,
		"categories": null,
		"live_status": "was_live",
		"was_live": true,
		"is_live": false,
		"media_type": "video",
		"webpage_url": "https://weverse.io/fiftyfifty/live/2-162812531",
		"subtitles": null,
		"thumbnail": "https://phinf.wevpstatic.net/MjAyNTA4MTFfMjQy/MDAxNzU0OTAzMzU3ODgw.Ifx8_ziHSIUsYlEBBtPz2NrVhxlRGouPmA2kGeKssTog.RRTb6tTsPAzXUe5IlybM6xzH5MJfV3RdtZu_p4TCsmcg.JPEG/thumb.jpg",
		"thumbnails": [
			{
				"url": "https://phinf.wevpstatic.net/MjAyNTA4MTFfMjQy/MDAxNzU0OTAzMzU3ODgw.Ifx8_ziHSIUsYlEBBtPz2NrVhxlRGouPmA2kGeKssTog.RRTb6tTsPAzXUe5IlybM6xzH5MJfV3RdtZu_p4TCsmcg.JPEG/thumb.jpg",
				"id": "0"
			}
		],
		"cast": ["HANA", "CHANELLE MOON"],
		"platform": "weverse",
		"series": null
	},
	{
		"id": "4-206297374",
		"title": "트웨니가 보고 싶어서~!!~!",
		"uploader": "HANA",
		"channel_id": "221",
		"channel_url": "https://weverse.io/fiftyfifty",
		"duration": 124.0,
		"duration_string": "2:04",
		"upload_date": "20250811",
		"timestamp": 1754899068,
		"view_count": 3147,
		"like_count": 4799,
		"release_timestamp": 1754899068,
		"comment_count": 10,
		"description": "하나 왔당☘️",
		"tags": null,
		"categories": null,
		"live_status": "was_live",
		"was_live": true,
		"is_live": false,
		"media_type": "video",
		"webpage_url": "https://weverse.io/fiftyfifty/live/4-206297374",
		"subtitles": null,
		"thumbnail": "https://phinf.wevpstatic.net/MjAyNTA4MTFfMTk4/MDAxNzU0ODk5MjA3MzU0.jBkGYcSa43cNCM-lcfrbYdhGxi3VH31J_cgbsTdDdPMg.u7J_-R_R2uM1c-WbMjiZhRksJqmYVW9blprTLLcF20sg.JPEG/thumb.jpg",
		"thumbnails": [
			{
				"url": "https://phinf.wevpstatic.net/MjAyNTA4MTFfMTk4/MDAxNzU0ODk5MjA3MzU0.jBkGYcSa43cNCM-lcfrbYdhGxi3VH31J_cgbsTdDdPMg.u7J_-R_R2uM1c-WbMjiZhRksJqmYVW9blprTLLcF20sg.JPEG/thumb.jpg",
				"id": "0"
			}
		],
		"cast": ["HANA"],
		"platform": "weverse",
		"series": null
	},
	{
		"id": "4-206274288",
		"title": "잠깐 틈나서 라방",
		"uploader": "KEENA",
		"channel_id": "221",
		"channel_url": "https://weverse.io/fiftyfifty",
		"duration": 814.0,
		"duration_string": "13:34",
		"upload_date": "20250811",
		"timestamp": 1754879053,
		"view_count": 6178,
		"like_count": 36521,
		"release_timestamp": 1754879053,
		"comment_count": 27,
		"description": "",
		"tags": null,
		"categories": null,
		"live_status": "was_live",
		"was_live": true,
		"is_live": false,
		"media_type": "video",
		"webpage_url": "https://weverse.io/fiftyfifty/live/4-206274288",
		"subtitles": null,
		"thumbnail": "https://phinf.wevpstatic.net/MjAyNTA4MTFfMjcz/MDAxNzU0ODc5MDM0NjQy.vKNYbmynZvUN5_oh7_DXMa4ibnn-P7XfIVb8JdPpTQ0g.LnrW4tHW4tvWse0ZWKq96EyZA2gstpmfU2fKhq1gWAEg.JPEG/image.jpg",
		"thumbnails": [
			{
				"url": "https://phinf.wevpstatic.net/MjAyNTA4MTFfMjcz/MDAxNzU0ODc5MDM0NjQy.vKNYbmynZvUN5_oh7_DXMa4ibnn-P7XfIVb8JdPpTQ0g.LnrW4tHW4tvWse0ZWKq96EyZA2gstpmfU2fKhq1gWAEg.JPEG/image.jpg",
				"id": "0"
			}
		],
		"cast": ["KEENA"],
		"platform": "weverse",
		"series": null
	},
	{
		"id": "1-162511133",
		"title": "✨dont change the channel✨",
		"uploader": "CHANELLE MOON",
		"channel_id": "221",
		"channel_url": "https://weverse.io/fiftyfifty",
		"duration": 4319.0,
		"duration_string": "1:11:59",
		"upload_date": "20250804",
		"timestamp": 1754301756,
		"view_count": 21189,
		"like_count": 138689,
		"release_timestamp": 1754301756,
		"comment_count": 36,
		"description": "",
		"tags": null,
		"categories": null,
		"live_status": "was_live",
		"was_live": true,
		"is_live": false,
		"media_type": "video",
		"webpage_url": "https://weverse.io/fiftyfifty/live/1-162511133",
		"subtitles": null,
		"thumbnail": "https://phinf.wevpstatic.net/MjAyNTA4MDVfMTk3/MDAxNzU0MzU1MTkwNTc5.eCzf0PH23iJ053JmFDEt8Miz1X3S9xoNm0JwimCoawQg.4h_anzwUOSEJFfpzx_AIC8KemQtv6HjIn5NVnBJ_Njsg.JPEG/snapshot_9bde1758-2eee-4715-b4c9-9d7844b7e0bd.jpg",
		"thumbnails": [
			{
				"url": "https://phinf.wevpstatic.net/MjAyNTA4MDVfMTk3/MDAxNzU0MzU1MTkwNTc5.eCzf0PH23iJ053JmFDEt8Miz1X3S9xoNm0JwimCoawQg.4h_anzwUOSEJFfpzx_AIC8KemQtv6HjIn5NVnBJ_Njsg.JPEG/snapshot_9bde1758-2eee-4715-b4c9-9d7844b7e0bd.jpg",
				"id": "0"
			}
		],
		"cast": ["CHANELLE MOON"],
		"platform": "weverse",
		"series": null
	},
	{
		"id": "3-205292349",
		"title": "밥.",
		"uploader": "FIFTY FIFTY",
		"channel_id": "221",
		"channel_url": "https://weverse.io/fiftyfifty",
		"duration": 2971.0,
		"duration_string": "49:31",
		"upload_date": "20250730",
		"timestamp": 1753877441,
		"view_count": 11913,
		"like_count": 87744,
		"release_timestamp": 1753877441,
		"comment_count": 32,
		"description": "",
		"tags": null,
		"categories": null,
		"live_status": "was_live",
		"was_live": true,
		"is_live": false,
		"media_type": "video",
		"webpage_url": "https://weverse.io/fiftyfifty/live/3-205292349",
		"subtitles": null,
		"thumbnail": "https://phinf.wevpstatic.net/MjAyNTA3MzBfMTAg/MDAxNzUzODc3NDI0Nzgx.NZTVJJJLv0FgYoCu4Sq9b7H8qRw1wyKl1tT0Nh7zC8Ug.gEWehhtqEEOATGn0WgN-ktQEjt_P-eg-zEMaHNLVqQkg.JPEG/image.jpg",
		"thumbnails": [
			{
				"url": "https://phinf.wevpstatic.net/MjAyNTA3MzBfMTAg/MDAxNzUzODc3NDI0Nzgx.NZTVJJJLv0FgYoCu4Sq9b7H8qRw1wyKl1tT0Nh7zC8Ug.gEWehhtqEEOATGn0WgN-ktQEjt_P-eg-zEMaHNLVqQkg.JPEG/image.jpg",
				"id": "0"
			}
		],
		"cast": ["KEENA"],
		"platform": "weverse",
		"series": null
	},
	{
		"id": "3-205107605",
		"title": "예원이의 고민상담소",
		"uploader": "FIFTY FIFTY",
		"channel_id": "221",
		"channel_url": "https://weverse.io/fiftyfifty",
		"duration": 3403.0,
		"duration_string": "56:43",
		"upload_date": "20250728",
		"timestamp": 1753668081,
		"view_count": 15550,
		"like_count": 80680,
		"release_timestamp": 1753668081,
		"comment_count": 32,
		"description": "",
		"tags": null,
		"categories": null,
		"live_status": "was_live",
		"was_live": true,
		"is_live": false,
		"media_type": "video",
		"webpage_url": "https://weverse.io/fiftyfifty/live/3-205107605",
		"subtitles": null,
		"thumbnail": "https://phinf.wevpstatic.net/MjAyNTA3MjhfMjg0/MDAxNzUzNjY4MDY0ODY4.FAgUhbwxw6VcZURu5WX3MulgZ0ry4zxDvEvjyNhkp10g.PNHLcFemlh22Pf_69E18jYwC37Px0TrVwKhu_HLTOpcg.JPEG/image.jpg",
		"thumbnails": [
			{
				"url": "https://phinf.wevpstatic.net/MjAyNTA3MjhfMjg0/MDAxNzUzNjY4MDY0ODY4.FAgUhbwxw6VcZURu5WX3MulgZ0ry4zxDvEvjyNhkp10g.PNHLcFemlh22Pf_69E18jYwC37Px0TrVwKhu_HLTOpcg.JPEG/image.jpg",
				"id": "0"
			}
		],
		"cast": ["YEWON"],
		"platform": "weverse",
		"series": null
	},
	{
		"id": "2-161517660",
		"title": "FIFTY FIFTY 5인 LIVE 🦊🧸🐰☘️🐥",
		"uploader": "FIFTY FIFTY",
		"channel_id": "221",
		"channel_url": "https://weverse.io/fiftyfifty",
		"duration": 3473.0,
		"duration_string": "57:53",
		"upload_date": "20250717",
		"timestamp": 1752746422,
		"view_count": 15641,
		"like_count": 155467,
		"release_timestamp": 1752746422,
		"comment_count": 27,
		"description": "해당 라이브에서 TWENY의 질문을 받아 FIFTY FIFTY 멤버들이 답변해드릴 예정입니다.\nTWENY의 많은 관심과 참여 부탁드립니다.\n\n📝 Q\u0026A form\n🔗 https://forms.gle/DcY8TRbuzhucSYDw7\n\n#FIFTYFIFTY #피프티피프티",
		"tags": null,
		"categories": null,
		"live_status": "was_live",
		"was_live": true,
		"is_live": false,
		"media_type": "video",
		"webpage_url": "https://weverse.io/fiftyfifty/live/2-161517660",
		"subtitles": null,
		"thumbnail": "https://phinf.wevpstatic.net/MjAyNTA3MDlfMjcy/MDAxNzUyMDI2OTg0Mzk5.Zjc_b5Yl8KwMs_VL5AWkEYx-TbM_UoPWtDwjLqNtTwIg.z2aL5kybnvVOvxAvKIZbMqpXc1qXEACx4NNOuG_LcCkg.JPEG/c74f4bbf-6cf2-4faa-85de-89aaabe283ae.jpeg",
		"thumbnails": [
			{
				"url": "https://phinf.wevpstatic.net/MjAyNTA3MDlfMjcy/MDAxNzUyMDI2OTg0Mzk5.Zjc_b5Yl8KwMs_VL5AWkEYx-TbM_UoPWtDwjLqNtTwIg.z2aL5kybnvVOvxAvKIZbMqpXc1qXEACx4NNOuG_LcCkg.JPEG/c74f4bbf-6cf2-4faa-85de-89aaabe283ae.jpeg",
				"id": "0"
			}
		],
		"cast": ["CHANELLE MOON", "KEENA", "HANA", "ATHENA", "YEWON"],
		"platform": "weverse",
		"series": null
	},
	{
		"id": "4-204170937",
		"title": "보고싶어여",
		"uploader": "ATHENA",
		"channel_id": "221",
		"channel_url": "https://weverse.io/fiftyfifty",
		"duration": 3511.0,
		"duration_string": "58:31",
		"upload_date": "20250715",
		"timestamp": 1752559400,
		"view_count": 52629,
		"like_count": 116776,
		"release_timestamp": 1752559400,
		"comment_count": 18,
		"description": "",
		"tags": null,
		"categories": null,
		"live_status": "was_live",
		"was_live": true,
		"is_live": false,
		"media_type": "video",
		"webpage_url": "https://weverse.io/fiftyfifty/live/4-204170937",
		"subtitles": null,
		"thumbnail": "https://phinf.wevpstatic.net/MjAyNTA3MTVfMjk3/MDAxNzUyNTYyOTIzMzAw.enmGWvRvD3skXIWHP4LKaGp79tjNjJn9tn85kHO7Xu0g.u3mAJJz-EfFxt3Sh5lOPLI33oQbxmlyBre1A6P2DGSIg.JPEG/thumb.jpg",
		"thumbnails": [
			{
				"url": "https://phinf.wevpstatic.net/MjAyNTA3MTVfMjk3/MDAxNzUyNTYyOTIzMzAw.enmGWvRvD3skXIWHP4LKaGp79tjNjJn9tn85kHO7Xu0g.u3mAJJz-EfFxt3Sh5lOPLI33oQbxmlyBre1A6P2DGSIg.JPEG/thumb.jpg",
				"id": "0"
			}
		],
		"cast": ["ATHENA"],
		"platform": "weverse",
		"series": null
	},
	{
		"id": "3-204176389",
		"title": "보고싶어여",
		"uploader": "ATHENA",
		"channel_id": "221",
		"channel_url": "https://weverse.io/fiftyfifty",
		"duration": 46.0,
		"duration_string": "46",
		"upload_date": "20250715",
		"timestamp": 1752559318,
		"view_count": 3890,
		"like_count": 1,
		"release_timestamp": 1752559318,
		"comment_count": 29,
		"description": "",
		"tags": null,
		"categories": null,
		"live_status": "was_live",
		"was_live": true,
		"is_live": false,
		"media_type": "video",
		"webpage_url": "https://weverse.io/fiftyfifty/live/3-204176389",
		"subtitles": null,
		"thumbnail": "https://phinf.wevpstatic.net/MjAyNTA3MTVfMTYx/MDAxNzUyNTU5Mzc0ODk1.18oeQOohVc4LKba1CvbavSvZ6mquZzQrye1NXltRjYcg.2lWttHVBVgHDvvP-YHQmCea7q5u7yGeNELsYbG-cWpsg.JPEG/thumb.jpg",
		"thumbnails": [
			{
				"url": "https://phinf.wevpstatic.net/MjAyNTA3MTVfMTYx/MDAxNzUyNTU5Mzc0ODk1.18oeQOohVc4LKba1CvbavSvZ6mquZzQrye1NXltRjYcg.2lWttHVBVgHDvvP-YHQmCea7q5u7yGeNELsYbG-cWpsg.JPEG/thumb.jpg",
				"id": "0"
			}
		],
		"cast": ["ATHENA"],
		"platform": "weverse",
		"series": null
	},
	{
		"id": "4-204046842",
		"title": "같이 저녁먹자 트웨니",
		"uploader": "KEENA",
		"channel_id": "221",
		"channel_url": "https://weverse.io/fiftyfifty",
		"duration": 3995.0,
		"duration_string": "1:06:35",
		"upload_date": "20250713",
		"timestamp": 1752415975,
		"view_count": 22722,
		"like_count": 191117,
		"release_timestamp": 1752415975,
		"comment_count": 19,
		"description": "같이 저녁묵자 우리 보고싶었어🤍",
		"tags": null,
		"categories": null,
		"live_status": "was_live",
		"was_live": true,
		"is_live": false,
		"media_type": "video",
		"webpage_url": "https://weverse.io/fiftyfifty/live/4-204046842",
		"subtitles": null,
		"thumbnail": "https://phinf.wevpstatic.net/MjAyNTA3MTRfMTc3/MDAxNzUyNDIwMDgxMzg5.1sBLhRmKy7Qzf86Uo9cc5zlomN4KjP4IF_5osYL0PZYg.UzViL4uYtVCWSxcdfWkhbHCeLjf61ehFTE5oQ99Uclog.JPEG/thumb.jpg",
		"thumbnails": [
			{
				"url": "https://phinf.wevpstatic.net/MjAyNTA3MTRfMTc3/MDAxNzUyNDIwMDgxMzg5.1sBLhRmKy7Qzf86Uo9cc5zlomN4KjP4IF_5osYL0PZYg.UzViL4uYtVCWSxcdfWkhbHCeLjf61ehFTE5oQ99Uclog.JPEG/thumb.jpg",
				"id": "0"
			}
		],
		"cast": ["KEENA"],
		"platform": "weverse",
		"series": null
	},
	{
		"id": "2-161629226",
		"title": "대만 룸메즈",
		"uploader": "ATHENA",
		"channel_id": "221",
		"channel_url": "https://weverse.io/fiftyfifty",
		"duration": 4054.0,
		"duration_string": "1:07:34",
		"upload_date": "20250712",
		"timestamp": 1752303603,
		"view_count": 30321,
		"like_count": 169343,
		"release_timestamp": 1752303603,
		"comment_count": 20,
		"description": "그냥 보고싶어서 ㅎㅎㅎ",
		"tags": null,
		"categories": null,
		"live_status": "was_live",
		"was_live": true,
		"is_live": false,
		"media_type": "video",
		"webpage_url": "https://weverse.io/fiftyfifty/live/2-161629226",
		"subtitles": null,
		"thumbnail": "https://phinf.wevpstatic.net/MjAyNTA3MTJfMTM3/MDAxNzUyMzAzNTkwOTk5.uIIgDcEZEjfz7KHSowTP0tslh2hquHhr-Jxl6h0yrlQg.CyKjV1vOjIAMGlsYVxj_sh4ZnsDNJKkXeD7wge-qmkUg.JPEG/Weverse_739e6.jpg",
		"thumbnails": [
			{
				"url": "https://phinf.wevpstatic.net/MjAyNTA3MTJfMTM3/MDAxNzUyMzAzNTkwOTk5.uIIgDcEZEjfz7KHSowTP0tslh2hquHhr-Jxl6h0yrlQg.CyKjV1vOjIAMGlsYVxj_sh4ZnsDNJKkXeD7wge-qmkUg.JPEG/Weverse_739e6.jpg",
				"id": "0"
			}
		],
		"cast": ["ATHENA", "YEWON", "HANA", "CHANELLE MOON"],
		"platform": "weverse",
		"series": null
	},
	{
		"id": "4-198077983",
		"title": "How was your children\u0027s day?👼💛",
		"uploader": "FIFTY FIFTY",
		"channel_id": "221",
		"channel_url": "https://weverse.io/fiftyfifty",
		"duration": 3985.0,
		"duration_string": "1:06:25",
		"upload_date": "20250505",
		"timestamp": 1746421221,
		"view_count": 19494,
		"like_count": 159628,
		"release_timestamp": 1746421221,
		"comment_count": 24,
		"description": "How was your children\u0027s day?👼💛\n2025. 05. 05 2PM (KST)\nWeverse Live\n\n#FIFTYFIFTY #피프티피프티\n#FIFTYFIFTY_DayAndNight\n#DayAndNight #Pookie\n#피프티피프티_Pookie",
		"tags": null,
		"categories": null,
		"live_status": "was_live",
		"was_live": true,
		"is_live": false,
		"media_type": "video",
		"webpage_url": "https://weverse.io/fiftyfifty/live/4-198077983",
		"subtitles": null,
		"thumbnail": "https://phinf.wevpstatic.net/MjAyNTA1MDJfNTIg/MDAxNzQ2MTYwNjE5NjE2.oP-K-St3hxLuVDv-7g6131zuXi-53EpeewiIFk-f8Lkg.-9-pH6_A8xA8oCjF7B2vMYt2fMKiipjsjLcPGci_2psg.JPEG/cbbc842a-a40b-4725-9e25-24fb71e1d65e.jpeg",
		"thumbnails": [
			{
				"url": "https://phinf.wevpstatic.net/MjAyNTA1MDJfNTIg/MDAxNzQ2MTYwNjE5NjE2.oP-K-St3hxLuVDv-7g6131zuXi-53EpeewiIFk-f8Lkg.-9-pH6_A8xA8oCjF7B2vMYt2fMKiipjsjLcPGci_2psg.JPEG/cbbc842a-a40b-4725-9e25-24fb71e1d65e.jpeg",
				"id": "0"
			}
		],
		"cast": ["ATHENA", "YEWON", "HANA", "CHANELLE MOON"],
		"platform": "weverse",
		"series": null
	},
	{
		"id": "3-197207683",
		"title": "Welcome to the DRAMA CLUB in FIFTY\u0027s NIGHT📺🌃",
		"uploader": "FIFTY FIFTY",
		"channel_id": "221",
		"channel_url": "https://weverse.io/fiftyfifty",
		"duration": 3926.0,
		"duration_string": "1:05:26",
		"upload_date": "20250425",
		"timestamp": 1745578908,
		"view_count": 13476,
		"like_count": 128490,
		"release_timestamp": 1745578908,
		"comment_count": 21,
		"description": "",
		"tags": null,
		"categories": null,
		"live_status": "was_live",
		"was_live": true,
		"is_live": false,
		"media_type": "video",
		"webpage_url": "https://weverse.io/fiftyfifty/live/3-197207683",
		"subtitles": null,
		"thumbnail": "https://phinf.wevpstatic.net/MjAyNTA0MjFfMTA3/MDAxNzQ1MjE2Mzc3NjQ3.5nO_fszbpg1KK2m_WkVTUExKykqxl0fBdq3ML09coYEg.DhkUMs3zNXKtyiOhC_UtU21pUanfImC6AHKGOdjXQ8Eg.PNG/bfd6880d-e4c3-49fc-a010-d8ee1718e994.png",
		"thumbnails": [
			{
				"url": "https://phinf.wevpstatic.net/MjAyNTA0MjFfMTA3/MDAxNzQ1MjE2Mzc3NjQ3.5nO_fszbpg1KK2m_WkVTUExKykqxl0fBdq3ML09coYEg.DhkUMs3zNXKtyiOhC_UtU21pUanfImC6AHKGOdjXQ8Eg.PNG/bfd6880d-e4c3-49fc-a010-d8ee1718e994.png",
				"id": "0"
			}
		],
		"cast": ["YEWON", "HANA", "KEENA"],
		"platform": "weverse",
		"series": null
	},
	{
		"id": "4-197202881",
		"title": "A or B DAY⁉️BALANCE GAME with TWENY🎲",
		"uploader": "FIFTY FIFTY",
		"channel_id": "221",
		"channel_url": "https://weverse.io/fiftyfifty",
		"duration": 3757.0,
		"duration_string": "1:02:37",
		"upload_date": "20250424",
		"timestamp": 1745474419,
		"view_count": 10893,
		"like_count": 97796,
		"release_timestamp": 1745474419,
		"comment_count": 21,
		"description": "",
		"tags": null,
		"categories": null,
		"live_status": "was_live",
		"was_live": true,
		"is_live": false,
		"media_type": "video",
		"webpage_url": "https://weverse.io/fiftyfifty/live/4-197202881",
		"subtitles": null,
		"thumbnail": "https://phinf.wevpstatic.net/MjAyNTA0MjFfMjA5/MDAxNzQ1MjE2MzMyNzc4.hW7CoYdtm1r8oXK-hV_fGXV6EBpP6Nvhl0iqi7EMncYg.ptDBuEpo4aL4yqamy_ITPBIPhJP2Z-p4Wp3K9RFyFu8g.PNG/0e54f1e2-3c89-4500-9753-3bedd59ae127.png",
		"thumbnails": [
			{
				"url": "https://phinf.wevpstatic.net/MjAyNTA0MjFfMjA5/MDAxNzQ1MjE2MzMyNzc4.hW7CoYdtm1r8oXK-hV_fGXV6EBpP6Nvhl0iqi7EMncYg.ptDBuEpo4aL4yqamy_ITPBIPhJP2Z-p4Wp3K9RFyFu8g.PNG/0e54f1e2-3c89-4500-9753-3bedd59ae127.png",
				"id": "0"
			}
		],
		"cast": ["ATHENA", "HANA"],
		"platform": "weverse",
		"series": null
	},
	{
		"id": "2-158268183",
		"title": "FIFTY FIFTY\u0027S NIGHT🌙 PLAYLIST with TWENTY🎧🎶",
		"uploader": "FIFTY FIFTY",
		"channel_id": "221",
		"channel_url": "https://weverse.io/fiftyfifty",
		"duration": 3941.0,
		"duration_string": "1:05:41",
		"upload_date": "20250423",
		"timestamp": 1745402417,
		"view_count": 14801,
		"like_count": 123737,
		"release_timestamp": 1745402417,
		"comment_count": 25,
		"description": "",
		"tags": null,
		"categories": null,
		"live_status": "was_live",
		"was_live": true,
		"is_live": false,
		"media_type": "video",
		"webpage_url": "https://weverse.io/fiftyfifty/live/2-158268183",
		"subtitles": null,
		"thumbnail": "https://phinf.wevpstatic.net/MjAyNTA0MjFfMTUg/MDAxNzQ1MjE2MjgxMDgw.1AP8ZBEafydVQMznBfgrGDRX-kMDFUz_kKCmkhgmF18g.7UZUJBS5ppl0T_IjNovN0jmzL6os01tU4rqEMfAeZzIg.PNG/ed018629-a6c0-4b45-8692-0194d366bfd8.png",
		"thumbnails": [
			{
				"url": "https://phinf.wevpstatic.net/MjAyNTA0MjFfMTUg/MDAxNzQ1MjE2MjgxMDgw.1AP8ZBEafydVQMznBfgrGDRX-kMDFUz_kKCmkhgmF18g.7UZUJBS5ppl0T_IjNovN0jmzL6os01tU4rqEMfAeZzIg.PNG/ed018629-a6c0-4b45-8692-0194d366bfd8.png",
				"id": "0"
			}
		],
		"cast": ["ATHENA", "CHANELLE MOON"],
		"platform": "weverse",
		"series": null
	},
	{
		"id": "4-196977126",
		"title": "KEENA\u0027S DAY ☀ ~결정의 신 키나편~ 무엇이던지 키나가 대신 정해드립니다!🔍📖",
		"uploader": "FIFTY FIFTY",
		"channel_id": "221",
		"channel_url": "https://weverse.io/fiftyfifty",
		"duration": 3572.0,
		"duration_string": "59:32",
		"upload_date": "20250422",
		"timestamp": 1745298038,
		"view_count": 12087,
		"like_count": 120173,
		"release_timestamp": 1745298038,
		"comment_count": 29,
		"description": "",
		"tags": null,
		"categories": null,
		"live_status": "was_live",
		"was_live": true,
		"is_live": false,
		"media_type": "video",
		"webpage_url": "https://weverse.io/fiftyfifty/live/4-196977126",
		"subtitles": null,
		"thumbnail": "https://phinf.wevpstatic.net/MjAyNTA0MThfNDEg/MDAxNzQ0OTYwMTg4NDM3.78QE2_AHNIpdqNzqL16MWIcW-4DVuWM0kcQg60hdbJUg.e1VcHVnZkg54_N6AmH_wCHQUy4QEvtR4IdNY7uXkEKMg.PNG/ef67d3d2-281f-4294-b95f-2c2d8c8c0e81.png",
		"thumbnails": [
			{
				"url": "https://phinf.wevpstatic.net/MjAyNTA0MThfNDEg/MDAxNzQ0OTYwMTg4NDM3.78QE2_AHNIpdqNzqL16MWIcW-4DVuWM0kcQg60hdbJUg.e1VcHVnZkg54_N6AmH_wCHQUy4QEvtR4IdNY7uXkEKMg.PNG/ef67d3d2-281f-4294-b95f-2c2d8c8c0e81.png",
				"id": "0"
			}
		],
		"cast": ["KEENA"],
		"platform": "weverse",
		"series": null
	},
	{
		"id": "3-196808184",
		"title": "FIFTY FIFTY\u0027S MYSTERY NIGHT🌙🐢🍲",
		"uploader": "FIFTY FIFTY",
		"channel_id": "221",
		"channel_url": "https://weverse.io/fiftyfifty",
		"duration": 3576.0,
		"duration_string": "59:36",
		"upload_date": "20250419",
		"timestamp": 1745070966,
		"view_count": 14627,
		"like_count": 113237,
		"release_timestamp": 1745070966,
		"comment_count": 29,
		"description": "",
		"tags": null,
		"categories": null,
		"live_status": "was_live",
		"was_live": true,
		"is_live": false,
		"media_type": "video",
		"webpage_url": "https://weverse.io/fiftyfifty/live/3-196808184",
		"subtitles": null,
		"thumbnail": "https://phinf.wevpstatic.net/MjAyNTA0MTVfMTYw/MDAxNzQ0NzA1Mjk4MTIy.ChJN5pJUb-MMA5__7iHFdOJDURE_Fm9cpDELuaJrVasg.mghQdPj2xQl4cQEtiFHBSWFqewPha1_aFTkb21KVjM8g.JPEG/20b39a7a-3255-4ae9-a149-3f46e357048c.jpeg",
		"thumbnails": [
			{
				"url": "https://phinf.wevpstatic.net/MjAyNTA0MTVfMTYw/MDAxNzQ0NzA1Mjk4MTIy.ChJN5pJUb-MMA5__7iHFdOJDURE_Fm9cpDELuaJrVasg.mghQdPj2xQl4cQEtiFHBSWFqewPha1_aFTkb21KVjM8g.JPEG/20b39a7a-3255-4ae9-a149-3f46e357048c.jpeg",
				"id": "0"
			}
		],
		"cast": ["YEWON", "ATHENA"],
		"platform": "weverse",
		"series": null
	},
	{
		"id": "2-157926077",
		"title": "FIFTY FIFTY\u0027S DAY☀ PLAYLIST with TWENY💿🎧🎶",
		"uploader": "FIFTY FIFTY",
		"channel_id": "221",
		"channel_url": "https://weverse.io/fiftyfifty",
		"duration": 4159.0,
		"duration_string": "1:09:19",
		"upload_date": "20250416",
		"timestamp": 1744776376,
		"view_count": 15256,
		"like_count": 126144,
		"release_timestamp": 1744776376,
		"comment_count": 36,
		"description": "",
		"tags": null,
		"categories": null,
		"live_status": "was_live",
		"was_live": true,
		"is_live": false,
		"media_type": "video",
		"webpage_url": "https://weverse.io/fiftyfifty/live/2-157926077",
		"subtitles": null,
		"thumbnail": "https://phinf.wevpstatic.net/MjAyNTA0MTBfMTc1/MDAxNzQ0MjcwMzU2MTU4.xtt8sTLt1a-AqrlIJUDorxrzk8Kf7fEzRFQYVE5v5-4g.ZtP4AFKJTiQLE9AS3EEmUanQcYEiMxNzetrq3nO0B5Qg.PNG/45bdd119-88db-4b78-9583-c67a103b0f33.png",
		"thumbnails": [
			{
				"url": "https://phinf.wevpstatic.net/MjAyNTA0MTBfMTc1/MDAxNzQ0MjcwMzU2MTU4.xtt8sTLt1a-AqrlIJUDorxrzk8Kf7fEzRFQYVE5v5-4g.ZtP4AFKJTiQLE9AS3EEmUanQcYEiMxNzetrq3nO0B5Qg.PNG/45bdd119-88db-4b78-9583-c67a103b0f33.png",
				"id": "0"
			}
		],
		"cast": ["YEWON", "ATHENA"],
		"platform": "weverse",
		"series": null
	},
	{
		"id": "4-196129488",
		"title": "WHAT IS YOUR CODENAME? #3 (w. 🐥🌱)",
		"uploader": "FIFTY FIFTY",
		"channel_id": "221",
		"channel_url": "https://weverse.io/fiftyfifty",
		"duration": 3665.0,
		"duration_string": "1:01:05",
		"upload_date": "20250405",
		"timestamp": 1743830122,
		"view_count": 15564,
		"like_count": 120049,
		"release_timestamp": 1743830122,
		"comment_count": 21,
		"description": "",
		"tags": null,
		"categories": null,
		"live_status": "was_live",
		"was_live": true,
		"is_live": false,
		"media_type": "video",
		"webpage_url": "https://weverse.io/fiftyfifty/live/4-196129488",
		"subtitles": null,
		"thumbnail": "https://phinf.wevpstatic.net/MjAyNTA0MDRfMjc5/MDAxNzQzNzU2NzMzODEw.Znb9V9ZyoqSLOd0KvmKxpgKv5YPDZPWOj6a79B6MOwcg.z3cTkteJCT5NqcIAPZpFAuhTVYTwJayqdI8L9aM145Mg.PNG/a997b43c-844d-4a00-860a-ee6abc844a68.png",
		"thumbnails": [
			{
				"url": "https://phinf.wevpstatic.net/MjAyNTA0MDRfMjc5/MDAxNzQzNzU2NzMzODEw.Znb9V9ZyoqSLOd0KvmKxpgKv5YPDZPWOj6a79B6MOwcg.z3cTkteJCT5NqcIAPZpFAuhTVYTwJayqdI8L9aM145Mg.PNG/a997b43c-844d-4a00-860a-ee6abc844a68.png",
				"id": "0"
			}
		],
		"cast": ["YEWON"],
		"platform": "weverse",
		"series": null
	},
	{
		"id": "2-157679118",
		"title": "WHAT IS YOUR CODENAME? #2 (w.🧃🔍💰🍖)",
		"uploader": "FIFTY FIFTY",
		"channel_id": "221",
		"channel_url": "https://weverse.io/fiftyfifty",
		"duration": 3850.0,
		"duration_string": "1:04:10",
		"upload_date": "20250403",
		"timestamp": 1743674444,
		"view_count": 12024,
		"like_count": 131617,
		"release_timestamp": 1743674444,
		"comment_count": 19,
		"description": "",
		"tags": null,
		"categories": null,
		"live_status": "was_live",
		"was_live": true,
		"is_live": false,
		"media_type": "video",
		"webpage_url": "https://weverse.io/fiftyfifty/live/2-157679118",
		"subtitles": null,
		"thumbnail": "https://phinf.wevpstatic.net/MjAyNTA0MDJfNTUg/MDAxNzQzNTc0NjE4NzI2.xkZOCS8ncGunMVmPSuS26wI82SCJEShqdOvguX2rfrAg.58pVCLreREkyP0mz_d5VTqHbVrursP-QiuL6sBDdtCAg.PNG/935e2a68-7106-4cc1-8cc0-7d18b336e8f0.png",
		"thumbnails": [
			{
				"url": "https://phinf.wevpstatic.net/MjAyNTA0MDJfNTUg/MDAxNzQzNTc0NjE4NzI2.xkZOCS8ncGunMVmPSuS26wI82SCJEShqdOvguX2rfrAg.58pVCLreREkyP0mz_d5VTqHbVrursP-QiuL6sBDdtCAg.PNG/935e2a68-7106-4cc1-8cc0-7d18b336e8f0.png",
				"id": "0"
			}
		],
		"cast": ["KEENA", "CHANELLE MOON"],
		"platform": "weverse",
		"series": null
	},
	{
		"id": "2-157597802",
		"title": "WHAT IS YOUR CODENAME?\n(w. 🎨🧤♠️🃏)",
		"uploader": "FIFTY FIFTY",
		"channel_id": "221",
		"channel_url": "https://weverse.io/fiftyfifty",
		"duration": 3490.0,
		"duration_string": "58:10",
		"upload_date": "20250401",
		"timestamp": 1743501662,
		"view_count": 12889,
		"like_count": 144821,
		"release_timestamp": 1743501662,
		"comment_count": 18,
		"description": "",
		"tags": null,
		"categories": null,
		"live_status": "was_live",
		"was_live": true,
		"is_live": false,
		"media_type": "video",
		"webpage_url": "https://weverse.io/fiftyfifty/live/2-157597802",
		"subtitles": null,
		"thumbnail": "https://phinf.wevpstatic.net/MjAyNTAzMzFfNzkg/MDAxNzQzMzk1NzUzMzEw.QxhY-e9YyooUPP-cesWXQ-BzpLCnMokKTvEDYlP6H-wg.VeU2Yt7sdc-lPZVY3QULD_qFlBVAprZNaBZInLgEcVgg.PNG/3017bc52-2d47-4f62-89e7-a69d5ad7955a.png",
		"thumbnails": [
			{
				"url": "https://phinf.wevpstatic.net/MjAyNTAzMzFfNzkg/MDAxNzQzMzk1NzUzMzEw.QxhY-e9YyooUPP-cesWXQ-BzpLCnMokKTvEDYlP6H-wg.VeU2Yt7sdc-lPZVY3QULD_qFlBVAprZNaBZInLgEcVgg.PNG/3017bc52-2d47-4f62-89e7-a69d5ad7955a.png",
				"id": "0"
			}
		],
		"cast": ["ATHENA", "HANA"],
		"platform": "weverse",
		"series": null
	},
	{
		"id": "3-194826564",
		"title": "트웨니 모해요",
		"uploader": "YEWON",
		"channel_id": "221",
		"channel_url": "https://weverse.io/fiftyfifty",
		"duration": 1131.0,
		"duration_string": "18:51",
		"upload_date": "20250317",
		"timestamp": 1742189863,
		"view_count": 6274,
		"like_count": 31658,
		"release_timestamp": 1742189863,
		"comment_count": 46,
		"description": "",
		"tags": null,
		"categories": null,
		"live_status": "was_live",
		"was_live": true,
		"is_live": false,
		"media_type": "voice only",
		"webpage_url": "https://weverse.io/fiftyfifty/live/3-194826564",
		"subtitles": null,
		"thumbnail": "https://phinf.wevpstatic.net/MjAyNDA0MDlfMTcx/MDAxNzEyNjQyMDYwNTY5.kZNwRC9suEwvYXqWuh8GSQNo8BEcOgzvKPZ3R5_fMFwg.riziFHxmDduqpxAyIEG6DNKMmNTFz7scJlPhx_mn4yUg.PNG/voice_p.png",
		"thumbnails": [
			{
				"url": "https://phinf.wevpstatic.net/MjAyNDA0MDlfMTcx/MDAxNzEyNjQyMDYwNTY5.kZNwRC9suEwvYXqWuh8GSQNo8BEcOgzvKPZ3R5_fMFwg.riziFHxmDduqpxAyIEG6DNKMmNTFz7scJlPhx_mn4yUg.PNG/voice_p.png",
				"id": "0"
			}
		],
		"cast": ["YEWON"],
		"platform": "weverse",
		"series": null
	},
	{
		"id": "0-156983049",
		"title": "방청소 할게요....",
		"uploader": "ATHENA",
		"channel_id": "221",
		"channel_url": "https://weverse.io/fiftyfifty",
		"duration": 1342.0,
		"duration_string": "22:22",
		"upload_date": "20250315",
		"timestamp": 1742023194,
		"view_count": 8069,
		"like_count": 57741,
		"release_timestamp": 1742023194,
		"comment_count": 32,
		"description": "",
		"tags": null,
		"categories": null,
		"live_status": "was_live",
		"was_live": true,
		"is_live": false,
		"media_type": "voice only",
		"webpage_url": "https://weverse.io/fiftyfifty/live/0-156983049",
		"subtitles": null,
		"thumbnail": "https://phinf.wevpstatic.net/MjAyNDA0MDlfMTcx/MDAxNzEyNjQyMDYwNTY5.kZNwRC9suEwvYXqWuh8GSQNo8BEcOgzvKPZ3R5_fMFwg.riziFHxmDduqpxAyIEG6DNKMmNTFz7scJlPhx_mn4yUg.PNG/voice_p.png",
		"thumbnails": [
			{
				"url": "https://phinf.wevpstatic.net/MjAyNDA0MDlfMTcx/MDAxNzEyNjQyMDYwNTY5.kZNwRC9suEwvYXqWuh8GSQNo8BEcOgzvKPZ3R5_fMFwg.riziFHxmDduqpxAyIEG6DNKMmNTFz7scJlPhx_mn4yUg.PNG/voice_p.png",
				"id": "0"
			}
		],
		"cast": ["YEWON", "ATHENA", "HANA"],
		"platform": "weverse",
		"series": null
	},
	{
		"id": "2-156990731",
		"title": "까꿍! 잠깐 생일이니까 ㅎㅎ",
		"uploader": "ATHENA",
		"channel_id": "221",
		"channel_url": "https://weverse.io/fiftyfifty",
		"duration": 1053.0,
		"duration_string": "17:33",
		"upload_date": "20250315",
		"timestamp": 1742009443,
		"view_count": 7420,
		"like_count": 43741,
		"release_timestamp": 1742009443,
		"comment_count": 43,
		"description": "zzz",
		"tags": null,
		"categories": null,
		"live_status": "was_live",
		"was_live": true,
		"is_live": false,
		"media_type": "video",
		"webpage_url": "https://weverse.io/fiftyfifty/live/2-156990731",
		"subtitles": null,
		"thumbnail": "https://phinf.wevpstatic.net/MjAyNDA0MDlfMTcx/MDAxNzEyNjQyMDYwNTY5.kZNwRC9suEwvYXqWuh8GSQNo8BEcOgzvKPZ3R5_fMFwg.riziFHxmDduqpxAyIEG6DNKMmNTFz7scJlPhx_mn4yUg.PNG/voice_p.png",
		"thumbnails": [
			{
				"url": "https://phinf.wevpstatic.net/MjAyNDA0MDlfMTcx/MDAxNzEyNjQyMDYwNTY5.kZNwRC9suEwvYXqWuh8GSQNo8BEcOgzvKPZ3R5_fMFwg.riziFHxmDduqpxAyIEG6DNKMmNTFz7scJlPhx_mn4yUg.PNG/voice_p.png",
				"id": "0"
			}
		],
		"cast": ["ATHENA"],
		"platform": "weverse",
		"series": null
	},
	{
		"id": "1-155704403",
		"title": "FIFTY FIFTY 막간 라이브🩷💙🦊🧸🐰☘️🐥",
		"uploader": "FIFTY FIFTY",
		"channel_id": "221",
		"channel_url": "https://weverse.io/fiftyfifty",
		"duration": 3111.0,
		"duration_string": "51:51",
		"upload_date": "20250212",
		"timestamp": 1739345421,
		"view_count": 14694,
		"like_count": 166034,
		"release_timestamp": 1739345421,
		"comment_count": 31,
		"description": "",
		"tags": null,
		"categories": null,
		"live_status": "was_live",
		"was_live": true,
		"is_live": false,
		"media_type": "video",
		"webpage_url": "https://weverse.io/fiftyfifty/live/1-155704403",
		"subtitles": null,
		"thumbnail": "https://phinf.wevpstatic.net/MjAyNTAyMTBfMjY2/MDAxNzM5MTUxNzI4ODkx.sC7lUtBWMp0w3CiOWG-n7e4HAhxNmz2jZ__IKgl4u7Ig.GUzsMy6W8vyIeoKGFpN-7C7X8wLoWcyaG8wbaZZ9Ggwg.JPEG/5fd83dd5-c5a7-4f2a-8b3f-8d8b431b6105.jpeg",
		"thumbnails": [
			{
				"url": "https://phinf.wevpstatic.net/MjAyNTAyMTBfMjY2/MDAxNzM5MTUxNzI4ODkx.sC7lUtBWMp0w3CiOWG-n7e4HAhxNmz2jZ__IKgl4u7Ig.GUzsMy6W8vyIeoKGFpN-7C7X8wLoWcyaG8wbaZZ9Ggwg.JPEG/5fd83dd5-c5a7-4f2a-8b3f-8d8b431b6105.jpeg",
				"id": "0"
			}
		],
		"cast": ["ATHENA", "YEWON", "HANA", "KEENA", "CHANELLE MOON"],
		"platform": "weverse",
		"series": null
	},
	{
		"id": "3-189184714",
		"title": "FIFTY FIFTY\u0027S HAPPY NEW YEAR SPECIAL LIVE 🎀🧹🐦‍⬛💚💗⚡",
		"uploader": "FIFTY FIFTY",
		"channel_id": "221",
		"channel_url": "https://weverse.io/fiftyfifty",
		"duration": 3402.0,
		"duration_string": "56:42",
		"upload_date": "20250107",
		"timestamp": 1736247659,
		"view_count": 21751,
		"like_count": 315754,
		"release_timestamp": 1736247659,
		"comment_count": 53,
		"description": "",
		"tags": null,
		"categories": null,
		"live_status": "was_live",
		"was_live": true,
		"is_live": false,
		"media_type": "video",
		"webpage_url": "https://weverse.io/fiftyfifty/live/3-189184714",
		"subtitles": null,
		"thumbnail": "https://phinf.wevpstatic.net/MjAyNTAxMDZfMjA3/MDAxNzM2MTM2MTA3MzUx.80G8SqFzXOtQLABWU6oPIKdL2DceIgea0Qhhm8L71tIg.WHXUdE5aTR-kwmsQT88NX7sjCSkm2X6wZ3sx3pmyIksg.JPEG/923dc595-8ebc-470d-adf4-1aa1d54a2444.jpeg",
		"thumbnails": [
			{
				"url": "https://phinf.wevpstatic.net/MjAyNTAxMDZfMjA3/MDAxNzM2MTM2MTA3MzUx.80G8SqFzXOtQLABWU6oPIKdL2DceIgea0Qhhm8L71tIg.WHXUdE5aTR-kwmsQT88NX7sjCSkm2X6wZ3sx3pmyIksg.JPEG/923dc595-8ebc-470d-adf4-1aa1d54a2444.jpeg",
				"id": "0"
			}
		],
		"cast": ["ATHENA", "YEWON", "HANA", "KEENA", "CHANELLE MOON"],
		"platform": "weverse",
		"series": null
	},
	{
		"id": "3-186515945",
		"title": "트웨니 여기여기 모여라😘💕",
		"uploader": "FIFTY FIFTY",
		"channel_id": "221",
		"channel_url": "https://weverse.io/fiftyfifty",
		"duration": 935.0,
		"duration_string": "15:35",
		"upload_date": "20241130",
		"timestamp": 1732957931,
		"view_count": 16718,
		"like_count": 95671,
		"release_timestamp": 1732957931,
		"comment_count": 170,
		"description": "",
		"tags": null,
		"categories": null,
		"live_status": "was_live",
		"was_live": true,
		"is_live": false,
		"media_type": "video",
		"webpage_url": "https://weverse.io/fiftyfifty/live/3-186515945",
		"subtitles": null,
		"thumbnail": "https://phinf.wevpstatic.net/MjAyNDExMzBfMTcz/MDAxNzMyOTU3OTE3NzYz.ie9Qwf82uCJKG59PcXyDdL_an9yfssVVdgveGMG-DWkg.6-2gkU9zYOkoJtQLTP9q8sOgrnlC1m2ndoIGp99Ih4Ug.JPEG/image.jpg",
		"thumbnails": [
			{
				"url": "https://phinf.wevpstatic.net/MjAyNDExMzBfMTcz/MDAxNzMyOTU3OTE3NzYz.ie9Qwf82uCJKG59PcXyDdL_an9yfssVVdgveGMG-DWkg.6-2gkU9zYOkoJtQLTP9q8sOgrnlC1m2ndoIGp99Ih4Ug.JPEG/image.jpg",
				"id": "0"
			}
		],
		"cast": ["ATHENA", "YEWON", "HANA", "KEENA", "CHANELLE MOON"],
		"platform": "weverse",
		"series": null
	}
]
